gleweather/__init__.py
gleweather/gleweather.py
gleweather-0.1.4.dist-info/LICENSE.txt
gleweather-0.1.4.dist-info/METADATA
gleweather-0.1.4.dist-info/WHEEL
gleweather-0.1.4.dist-info/top_level.txt
gleweather-0.1.4.dist-info/RECORD
